README.md
setup.cfg
setup.py
laocoon/__init__.py
laocoon/dapi_pipeline.py
laocoon/edu_pipeline.py
laocoon/equalization.py
laocoon/gfp_pipeline.py
laocoon/rfp_pipeline.py
laocoon.egg-info/PKG-INFO
laocoon.egg-info/SOURCES.txt
laocoon.egg-info/dependency_links.txt
laocoon.egg-info/requires.txt
laocoon.egg-info/top_level.txt