Metadata-Version: 1.1
Name: laocoon
Version: 0.1.1
Summary: Automatically and efficiently count the number of cells in a fluorescently stained image.
Home-page: https://github.com/edukait/laocoon
Author: Kaitlin Lim
Author-email: kaitlin.y.lim@gmail.com
License: MIT
Keywords: analysis,high-throughput,efficient
Platform: UNKNOWN
Classifier: Development Status :: 4 - Beta
Classifier: Intended Audience :: Science/Research
Classifier: Topic :: Software Development :: Build Tools
Classifier: License :: OSI Approved :: MIT License
Classifier: Programming Language :: Python :: 3
Classifier: Programming Language :: Python :: 3.4
Classifier: Programming Language :: Python :: 3.5
Classifier: Programming Language :: Python :: 3.6
Classifier: Programming Language :: Python :: 3.7
